npipes/__init__.py
npipes/consts.py
npipes/ipc.py
npipes/message.py
npipes/pipes.py
npipes-1.0.0.dist-info/LICENSE
npipes-1.0.0.dist-info/METADATA
npipes-1.0.0.dist-info/WHEEL
npipes-1.0.0.dist-info/top_level.txt
npipes-1.0.0.dist-info/RECORD
