Metadata-Version: 2.1
Name: npipes
Version: 1.0.0
Summary: Wrapper Library for Named Pipes
Home-page: https://github.com/mani-src/npipes.git
Author: Manikanta Ambadipudi
Author-email: ambadipudi.manikanta@gmail.com
License: UNKNOWN
Platform: UNKNOWN
Requires-Dist: pywin32
